napari_denoiseg/__init__.py
napari_denoiseg/_predict_widget.py
napari_denoiseg/_sample_data.py
napari_denoiseg/_threshold_widget.py
napari_denoiseg/_train_widget.py
napari_denoiseg/napari.yaml
napari_denoiseg/_tests/__init__.py
napari_denoiseg/_tests/test_axes_widget.py
napari_denoiseg/_tests/test_denoiseg_utils.py
napari_denoiseg/_tests/test_expert_settings.py
napari_denoiseg/_tests/test_io_utils.py
napari_denoiseg/_tests/test_load_images_utils.py
napari_denoiseg/_tests/test_optimizer_worker.py
napari_denoiseg/_tests/test_prediction_worker.py
napari_denoiseg/_tests/test_resources.py
napari_denoiseg/_tests/test_sample_data.py
napari_denoiseg/_tests/test_training_worker.py
napari_denoiseg/_tests/test_utils.py
napari_denoiseg/resources/__init__.py
napari_denoiseg/resources/resources.py
napari_denoiseg/utils/__init__.py
napari_denoiseg/utils/denoiseg_utils.py
napari_denoiseg/utils/expert_settings.py
napari_denoiseg/utils/io_utils.py
napari_denoiseg/utils/load_images_utils.py
napari_denoiseg/utils/loading_worker.py
napari_denoiseg/utils/optimizer_worker.py
napari_denoiseg/utils/prediction_worker.py
napari_denoiseg/utils/training_worker.py
napari_denoiseg/widgets/__init__.py
napari_denoiseg/widgets/axes_widget.py
napari_denoiseg/widgets/banner_widget.py
napari_denoiseg/widgets/expert_settings_widget.py
napari_denoiseg/widgets/folder_widget.py
napari_denoiseg/widgets/gpu_widget.py
napari_denoiseg/widgets/magicgui_widgets.py
napari_denoiseg/widgets/qt_widgets.py
napari_denoiseg/widgets/scroll_wrapper.py
napari_denoiseg/widgets/tbplot_widget.py
napari_denoiseg-0.0.1rc2.dist-info/LICENSE
napari_denoiseg-0.0.1rc2.dist-info/METADATA
napari_denoiseg-0.0.1rc2.dist-info/WHEEL
napari_denoiseg-0.0.1rc2.dist-info/entry_points.txt
napari_denoiseg-0.0.1rc2.dist-info/top_level.txt
napari_denoiseg-0.0.1rc2.dist-info/RECORD
