Metadata-Version: 2.1
Name: napari-denoiseg
Version: 0.0.1rc2
Summary: A napari plugin performing joint denoising and segmentation of microscopy images using DenoiSeg.
Home-page: https://github.com/juglab/napari_denoiseg
Author: Tom Burke, Joran Deschamps
Author-email: joran.deschamps@fht.org
License: BSD-3-Clause
Project-URL: Bug Tracker, https://github.com/juglab/napari_denoiseg/issues
Project-URL: Documentation, https://juglab.github.io/napari-denoiseg/
Project-URL: Source Code, https://github.com/juglab/napari_denoiseg
Project-URL: User Support, https://github.com/juglab/napari_denoiseg/issues
Classifier: Framework :: napari
Classifier: Development Status :: 3 - Alpha
Classifier: Intended Audience :: Science/Research
Classifier: Topic :: Scientific/Engineering :: Image Processing
Classifier: Topic :: Scientific/Engineering :: Information Analysis
Classifier: Programming Language :: Python
Classifier: Programming Language :: Python :: 3
Classifier: Programming Language :: Python :: 3.7
Classifier: Programming Language :: Python :: 3.8
Classifier: Programming Language :: Python :: 3.9
Classifier: Programming Language :: Python :: 3.10
Classifier: Operating System :: OS Independent
Classifier: License :: OSI Approved :: BSD License
Requires-Python: >=3.7
License-File: LICENSE
Requires-Dist: numpy
Requires-Dist: pyqtgraph
Requires-Dist: denoiseg (>=0.3.0)
Requires-Dist: bioimageio.core
Requires-Dist: magicgui
Requires-Dist: qtpy
Requires-Dist: napari-time-slicer (>=0.4.9)
Requires-Dist: napari (<=0.4.15)
Requires-Dist: vispy (<=0.9.6)
Requires-Dist: imageio (!=2.11.0,!=2.22.1,>=2.5.0)
Requires-Dist: tensorflow ; platform_system != "Darwin" or platform_machine != "arm64"
Requires-Dist: tensorflow-macos ; platform_system == "Darwin" and platform_machine == "arm64"
Requires-Dist: tensorflow-metal ; platform_system == "Darwin" and platform_machine == "arm64"
Provides-Extra: testing
Requires-Dist: pytest ; extra == 'testing'
Requires-Dist: pytest-cov ; extra == 'testing'
Requires-Dist: pytest-qt ; extra == 'testing'
Requires-Dist: pyqt5 ; extra == 'testing'
